e2xgrader_cell_registry/__init__.py
e2xgrader_cell_registry/_version.py
e2xgrader_cell_registry-0.0.1a2.data/data/share/jupyter/labextensions/@e2xgrader/cell-registry/package.json
e2xgrader_cell_registry-0.0.1a2.data/data/share/jupyter/labextensions/@e2xgrader/cell-registry/schemas/@e2xgrader/cell-registry/cell-factory.json
e2xgrader_cell_registry-0.0.1a2.data/data/share/jupyter/labextensions/@e2xgrader/cell-registry/schemas/@e2xgrader/cell-registry/package.json.orig
e2xgrader_cell_registry-0.0.1a2.data/data/share/jupyter/labextensions/@e2xgrader/cell-registry/static/357.5e897a840fe092a4b7f7.js
e2xgrader_cell_registry-0.0.1a2.data/data/share/jupyter/labextensions/@e2xgrader/cell-registry/static/728.770c73a857688d981455.js
e2xgrader_cell_registry-0.0.1a2.data/data/share/jupyter/labextensions/@e2xgrader/cell-registry/static/remoteEntry.a6d2672a064179e0e00a.js
e2xgrader_cell_registry-0.0.1a2.data/data/share/jupyter/labextensions/@e2xgrader/cell-registry/static/style.js
e2xgrader_cell_registry-0.0.1a2.data/data/share/jupyter/labextensions/@e2xgrader/cell-registry/static/third-party-licenses.json
e2xgrader_cell_registry-0.0.1a2.data/data/share/jupyter/labextensions/@e2xgrader/cell-registry/install.json
e2xgrader_cell_registry-0.0.1a2.dist-info/METADATA
e2xgrader_cell_registry-0.0.1a2.dist-info/WHEEL
e2xgrader_cell_registry-0.0.1a2.dist-info/licenses/LICENSE
e2xgrader_cell_registry-0.0.1a2.dist-info/RECORD
