Metadata-Version: 2.4
Name: e2xgrader_cell_registry
Version: 0.0.1a2
Summary: A JupyterLab extension for e2xgrader that provides a registry for custom cells
Project-URL: Homepage, https://github.com/e2xgrader/e2xgrader-cell-registry
Project-URL: Bug Tracker, https://github.com/e2xgrader/e2xgrader-cell-registry/issues
Project-URL: Repository, https://github.com/e2xgrader/e2xgrader-cell-registry.git
Author-email: Tim Metzler <tim.metzler@h-brs.de>
License: BSD 3-Clause License
License-File: LICENSE
Keywords: jupyter,jupyterlab,jupyterlab-extension
Classifier: Framework :: Jupyter
Classifier: Framework :: Jupyter :: JupyterLab
Classifier: Framework :: Jupyter :: JupyterLab :: 4
Classifier: Framework :: Jupyter :: JupyterLab :: Extensions
Classifier: Framework :: Jupyter :: JupyterLab :: Extensions :: Prebuilt
Classifier: License :: OSI Approved :: BSD License
Classifier: Programming Language :: Python
Classifier: Programming Language :: Python :: 3
Classifier: Programming Language :: Python :: 3.9
Classifier: Programming Language :: Python :: 3.10
Classifier: Programming Language :: Python :: 3.11
Classifier: Programming Language :: Python :: 3.12
Classifier: Programming Language :: Python :: 3.13
Requires-Python: >=3.9
